{
  "ux_evaluation_wave": {
    "cognitive_load_analysis": "The user needs to understand the system as a series of interconnected microservices, each with specific functionalities. Mental models should focus on input/output streams, configuration parameters, and observable metrics. The system should abstract away underlying infrastructure complexity.",
    "affordance_map": [
      {
        "element": "primary action buttons (e.g., 'Deploy', 'Configure', 'View Logs')",
        "visual_cue": "Prominent placement, distinct color contrast (e.g., brand-primary), clear iconography, and hover states.",
        "interaction": "Clickable, providing immediate feedback on press and state change."
      },
      {
        "element": "data visualization components (charts, graphs)",
        "visual_cue": "Clear axes labels, tooltips on hover, distinct color palettes for multiple data series, and dynamic updates.",
        "interaction": "Hover to reveal details, potential for drill-down or filtering."
      },
      {
        "element": "navigation elements (tabs, sidebar links)",
        "visual_cue": "Underlined active states, clear labels, consistent placement.",
        "interaction": "Clickable, triggering content changes without full page reload."
      },
      {
        "element": "input fields and controls (text areas, dropdowns, toggles)",
        "visual_cue": "Clear labels, appropriate input type hints, focus states, and validation feedback.",
        "interaction": "Editable, with immediate visual feedback on input and validation."
      }
    ],
    "gsap_animation_plan": [
      {
        "transition": "Page/section transitions",
        "animation": "Subtle fade-in/slide-up with slight stagger for content blocks to reduce perceived load.",
        "trigger": "Navigation changes, data loading."
      },
      {
        "transition": "Button click feedback",
        "animation": "Micro-scale scale-down/up on press, followed by a subtle color/border change to indicate processing. Subsequent state change animation (e.g., checkmark, spinner).",
        "trigger": "All primary and secondary interactive elements."
      },
      {
        "transition": "Data loading and updates",
        "animation": "Skeleton loaders or shimmering effects for new content areas, with smooth transitions for chart updates.",
        "trigger": "Asynchronous data fetches."
      },
      {
        "transition": "Expansion/collapse of information panels",
        "animation": "Smooth height transition with optional slight fade.",
        "trigger": "Accordions, expandable logs, detailed views."
      }
    ],
    "accessibility_checklist": [
      "WCAG 2.2 AA Level: Color contrast ratio minimum 4.5:1 for normal text and 3:1 for large text.",
      "Semantic HTML5: Use appropriate tags (nav, main, article, aside, header, footer, section).",
      "ARIA attributes: Use aria-label, aria-labelledby, aria-describedby, aria-haspopup, aria-expanded where necessary for interactive elements and dynamic content.",
      "Keyboard navigability: All interactive elements focusable and operable via keyboard (tab order logical, visible focus indicator).",
      "Focus management: Ensure focus is appropriately managed during dynamic content changes.",
      "Screen reader compatibility: Test with major screen readers (NVDA, JAWS, VoiceOver).",
      "Resizable text: Ensure UI remains usable when text is resized up to 200%.",
      "Clear focus indicators: Focus states must be highly visible."
    ],
    "sota_signals_integration": [
      "FastAPI + Pydantic v2 for async Python services.",
      "OpenFeature standard for feature flags (decoupling deployment from release, enabling hypothesis testing).",
      "DORA metrics (deploy frequency, lead time, MTTR, CFR) as core engineering strategy anchors.",
      "OpenTelemetry for distributed tracing and instrumentation.",
      "Structured logging (JSON + trace_id) for observability."
    ],
    "vlt_json": {
      "tree_id": "main-dashboard-vlt",
      "viewport_width": 1920,
      "viewport_height": 1080,
      "root_node": {
        "id": "app-root",
        "type": "Flex",
        "direction": "column",
        "gap": "8px",
        "padding": "32px",
        "children": [
          {
            "id": "header-section",
            "type": "Flex",
            "direction": "row",
            "justify": "between",
            "align": "center",
            "padding": "0px 16px",
            "height": "64px",
            "children": [
              {
                "id": "logo-container",
                "type": "Image",
                "src": "/static/logo.svg",
                "alt": "Company Logo",
                "width": "128px",
                "height": "auto"
              },
              {
                "id": "nav-primary",
                "type": "Nav",
                "children": [
                  {
                    "id": "nav-item-dashboard",
                    "type": "NavLink",
                    "text": "Dashboard",
                    "href": "/",
                    "padding": "8px 16px"
                  },
                  {
                    "id": "nav-item-services",
                    "type": "NavLink",
                    "text": "Services",
                    "href": "/services",
                    "padding": "8px 16px"
                  },
                  {
                    "id": "nav-item-settings",
                    "type": "NavLink",
                    "text": "Settings",
                    "href": "/settings",
                    "padding": "8px 16px"
                  }
                ]
              }
            ]
          },
          {
            "id": "main-content-area",
            "type": "Flex",
            "direction": "column",
            "gap": "32px",
            "padding": "0px",
            "children": [
              {
                "id": "stats-row",
                "type": "Flex",
                "direction": "row",
                "justify": "start",
                "gap": "32px",
                "padding": "0px",
                "children": [
                  {
                    "id": "stat-card-deploy-freq",
                    "type": "Card",
                    "width": "240px",
                    "padding": "24px",
                    "children": [
                      {
                        "id": "stat-title-deploy-freq",
                        "type": "Text",
                        "text": "Deploy Frequency",
                        "fontSize": "16px",
                        "fontWeight": "500"
                      },
                      {
                        "id": "stat-value-deploy-freq",
                        "type": "Text",
                        "text": "Daily",
                        "fontSize": "32px",
                        "fontWeight": "700"
                      }
                    ]
                  },
                  {
                    "id": "stat-card-lead-time",
                    "type": "Card",
                    "width": "240px",
                    "padding": "24px",
                    "children": [
                      {
                        "id": "stat-title-lead-time",
                        "type": "Text",
                        "text": "Lead Time",
                        "fontSize": "16px",
                        "fontWeight": "500"
                      },
                      {
                        "id": "stat-value-lead-time",
                        "type": "Text",
                        "text": "< 1 Hour",
                        "fontSize": "32px",
                        "fontWeight": "700"
                      }
                    ]
                  },
                  {
                    "id": "stat-card-mttr",
                    "type": "Card",
                    "width": "240px",
                    "padding": "24px",
                    "children": [
                      {
                        "id": "stat-title-mttr",
                        "type": "Text",
                        "text": "MTTR",
                        "fontSize": "16px",
                        "fontWeight": "500"
                      },
                      {
                        "id": "stat-value-mttr",
                        "type": "Text",
                        "text": "< 15 Min",
                        "fontSize": "32px",
                        "fontWeight": "700"
                      }
                    ]
                  },
                  {
                    "id": "stat-card-cfr",
                    "type": "Card",
                    "width": "240px",
                    "padding": "24px",
                    "children": [
                      {
                        "id": "stat-title-cfr",
                        "type": "Text",
                        "text": "Change Failure Rate",
                        "fontSize": "16px",
                        "fontWeight": "500"
                      },
                      {
                        "id": "stat-value-cfr",
                        "type": "Text",
                        "text": "< 5%",
                        "fontSize": "32px",
                        "fontWeight": "700"
                      }
                    ]
                  }
                ]
              },
              {
                "id": "service-health-overview",
                "type": "Card",
                "padding": "32px",
                "children": [
                  {
                    "id": "service-health-title",
                    "type": "Text",
                    "text": "Service Health Overview",
                    "fontSize": "24px",
                    "fontWeight": "700",
                    "marginBottom": "16px"
                  },
                  {
                    "id": "service-list",
                    "type": "Flex",
                    "direction": "column",
                    "gap": "16px",
                    "children": [
                      {
                        "id": "service-item-auth",
                        "type": "Flex",
                        "direction": "row",
                        "justify": "between",
                        "align": "center",
                        "children": [
                          {
                            "id": "service-name-auth",
                            "type": "Text",
                            "text": "Authentication Service",
                            "fontSize": "18px"
                          },
                          {
                            "id": "service-status-auth",
                            "type": "Badge",
                            "text": "Healthy",
                            "color": "green"
                          }
                        ]
                      },
                      {
                        "id": "service-item-user",
                        "type": "Flex",
                        "direction": "row",
                        "justify": "between",
                        "align": "center",
                        "children": [
                          {
                            "id": "service-name-user",
                            "type": "Text",
                            "text": "User Profile Service",
                            "fontSize": "18px"
                          },
                          {
                            "id": "service-status-user",
                            "type": "Badge",
                            "text": "Healthy",
                            "color": "green"
                          }
                        ]
                      },
                      {
                        "id": "service-item-payments",
                        "type": "Flex",
                        "direction": "row",
                        "justify": "between",
                        "align": "center",
                        "children": [
                          {
                            "id": "service-name-payments",
                            "type": "Text",
                            "text": "Payment Gateway",
                            "fontSize": "18px"
                          },
                          {
                            "id": "service-status-payments",
                            "type": "Badge",
                            "text": "Degraded",
                            "color": "orange"
                          }
                        ]
                      }
                    ]
                  }
                ]
              }
            ]
          }
        ]
      }
    }
  }
}
